NN/Perceptron.py
NN/__init__.py
NN/all_utils.py
Perceptron_PD_pypi-0.0.3.dist-info/LICENSE
Perceptron_PD_pypi-0.0.3.dist-info/METADATA
Perceptron_PD_pypi-0.0.3.dist-info/WHEEL
Perceptron_PD_pypi-0.0.3.dist-info/top_level.txt
Perceptron_PD_pypi-0.0.3.dist-info/RECORD
