Metadata-Version: 2.1
Name: Perceptron-PD-pypi
Version: 0.0.3
Summary: DESCRIPTION HERE
Home-page: https://github.com/Satyampd/Perceptron_PD_pypi
Author: Satyampd
Author-email: tiwarisatyampd@gmail.com
License: UNKNOWN
Project-URL: Bug Tracker, https://github.com/Satyampd/Perceptron_PD_pypi/issues
Platform: UNKNOWN
Classifier: Programming Language :: Python :: 3
Classifier: License :: OSI Approved :: MIT License
Classifier: Operating System :: OS Independent
Requires-Python: >=3.7
License-File: LICENSE
Requires-Dist: numpy
Requires-Dist: tqdm
Requires-Dist: joblib
Requires-Dist: matplotlib
